<?xml version="1.0" encoding="utf-8" ?>
<dwsync>
<file name="base.css" server="D:/Program Files/Apache Software Foundation/Tomcat 6.0/webapps/57game/" local="130497812660000000" remote="130497812660000000" Dst="0" />
<file name="btn.css" server="D:/Program Files/Apache Software Foundation/Tomcat 6.0/webapps/57game/" local="130498005900000000" remote="130498005900000000" Dst="0" />
<file name="footer.css" server="D:/Program Files/Apache Software Foundation/Tomcat 6.0/webapps/57game/" local="130488303400000000" remote="130488303400000000" Dst="0" />
<file name="form.css" server="D:/Program Files/Apache Software Foundation/Tomcat 6.0/webapps/57game/" local="130498004940000000" remote="130498004940000000" Dst="0" />
<file name="header.css" server="D:/Program Files/Apache Software Foundation/Tomcat 6.0/webapps/57game/" local="130488307520000000" remote="130488307520000000" Dst="0" />
<file name="icon.css" server="D:/Program Files/Apache Software Foundation/Tomcat 6.0/webapps/57game/" local="130497985360000000" remote="130497985360000000" Dst="0" />
<file name="index_style.css" server="D:/Program Files/Apache Software Foundation/Tomcat 6.0/webapps/57game/" local="130495192140000000" remote="130495192140000000" Dst="0" />
<file name="main.css" server="D:/Program Files/Apache Software Foundation/Tomcat 6.0/webapps/57game/" local="130498656440000000" remote="130498656440000000" Dst="0" />
<file name="reset.css" server="D:/Program Files/Apache Software Foundation/Tomcat 6.0/webapps/57game/" local="130496217880000000" remote="130496217880000000" Dst="0" />
<file name="sidebar.css" server="D:/Program Files/Apache Software Foundation/Tomcat 6.0/webapps/57game/" local="130495178060000000" remote="130495178060000000" Dst="0" />
<file name="style.css" server="D:/Program Files/Apache Software Foundation/Tomcat 6.0/webapps/57game/" local="130489123680000000" remote="130489123680000000" Dst="0" />
</dwsync>